odoo/addons/product_variant_name/README.rst
odoo/addons/product_variant_name/__init__.py
odoo/addons/product_variant_name/__manifest__.py
odoo/addons/product_variant_name/init_hook.py
odoo/addons/product_variant_name/i18n/es.po
odoo/addons/product_variant_name/i18n/it.po
odoo/addons/product_variant_name/i18n/product_variant_name.pot
odoo/addons/product_variant_name/models/__init__.py
odoo/addons/product_variant_name/models/product_product.py
odoo/addons/product_variant_name/models/product_template.py
odoo/addons/product_variant_name/readme/CONTRIBUTORS.md
odoo/addons/product_variant_name/readme/DESCRIPTION.md
odoo/addons/product_variant_name/static/description/icon.png
odoo/addons/product_variant_name/static/description/index.html
odoo/addons/product_variant_name/tests/__init__.py
odoo/addons/product_variant_name/tests/test_product_variant_name.py
odoo/addons/product_variant_name/views/product_view.xml
odoo_addon_product_variant_name-18.0.1.0.0.2.dist-info/METADATA
odoo_addon_product_variant_name-18.0.1.0.0.2.dist-info/WHEEL
odoo_addon_product_variant_name-18.0.1.0.0.2.dist-info/top_level.txt
odoo_addon_product_variant_name-18.0.1.0.0.2.dist-info/RECORD
